.git/HEAD
.git/config
.git/description
.git/hooks/applypatch-msg.sample
.git/hooks/commit-msg.sample
.git/hooks/fsmonitor-watchman.sample
.git/hooks/post-update.sample
.git/hooks/pre-applypatch.sample
.git/hooks/pre-commit.sample
.git/hooks/pre-merge-commit.sample
.git/hooks/pre-push.sample
.git/hooks/pre-rebase.sample
.git/hooks/pre-receive.sample
.git/hooks/prepare-commit-msg.sample
.git/hooks/push-to-checkout.sample
.git/hooks/sendemail-validate.sample
.git/hooks/update.sample
.git/index
.git/info/exclude
.git/logs/HEAD
.git/logs/refs/heads/main
.git/logs/refs/remotes/origin/HEAD
.git/objects/pack/pack-8eb56832798a4417a4b814085b787248a847729c.idx
.git/objects/pack/pack-8eb56832798a4417a4b814085b787248a847729c.pack
.git/objects/pack/pack-8eb56832798a4417a4b814085b787248a847729c.rev
.git/packed-refs
.git/refs/heads/main
.git/refs/remotes/origin/HEAD
LICENSE
README.md
__init__.py
cmd/__init__.py
cmd/adduser.py
cmd/antiout.py
cmd/authorinfo.py
cmd/baka.py
cmd/botid.py
cmd/configs/config.json
cmd/data/ApprovedThread.json
cmd/data/ApprovedUser.json
cmd/data/BannedThread.json
cmd/data/BannedUser.json
cmd/data/reasonForUserBan.json
cmd/echo.py
cmd/events/antiout.py
cmd/fbid.py
cmd/gpt.py
cmd/help.py
cmd/reload.py
cmd/removeuser.py
cmd/tid.py
cmd/topuser.py
cmd/uid.py
cmd/unsend.py
cmd/user.py
config.json
data.py
dist/togashibot-0.0.1.tar.gz
fbstate.json
handle/__init__.py
handle/handleCommands.py
handle/handleEvents.py
handle/handleMessage.py
handle/load_modules.py
main.py
poetry.lock
pyproject.toml
requirements.txt
src/welcome.webp
src/welcome1.gif
togashi_fbchat/__init__.py
togashi_fbchat/_attachment.py
togashi_fbchat/_client.py
togashi_fbchat/_core.py
togashi_fbchat/_exception.py
togashi_fbchat/_file.py
togashi_fbchat/_graphql.py
togashi_fbchat/_group.py
togashi_fbchat/_location.py
togashi_fbchat/_message.py
togashi_fbchat/_mqtt.py
togashi_fbchat/_page.py
togashi_fbchat/_plan.py
togashi_fbchat/_poll.py
togashi_fbchat/_quick_reply.py
togashi_fbchat/_state.py
togashibot-0.0.1.dist-info/LICENSE
togashibot-0.0.1.dist-info/METADATA
togashibot-0.0.1.dist-info/WHEEL
togashibot-0.0.1.dist-info/RECORD
