Metadata-Version: 2.1
Name: TogashiBot
Version: 0.0.1
Summary: A simple starter messenger bot using python
Home-page: https://github.com/togashigreat
Author: Muhammad MuQiT
Requires-Python: >=3.9,<4.0
Classifier: License :: OSI Approved :: MIT License
Classifier: Operating System :: OS Independent
Classifier: Programming Language :: Python :: 3
Classifier: Programming Language :: Python :: 3.9
Classifier: Programming Language :: Python :: 3.10
Classifier: Programming Language :: Python :: 3.11
Classifier: Programming Language :: Python :: 3.12
Classifier: Programming Language :: Python :: 3.13
Requires-Dist: aenum (>=2.0,<3.0)
Requires-Dist: attrs (==21.3)
Requires-Dist: beautifulsoup4 (>=4.0.0,<5.0.0)
Requires-Dist: httpx (==0.25.1)
Requires-Dist: openai (==1.3.5)
Requires-Dist: paho-mqtt (>=1.5.0,<2.0.0)
Requires-Dist: pydantic (==1.10.9)
Requires-Dist: requests (>=2.25.1,<3.0.0)
